Workbook

Sheet Assumptions
A1: EMMA™ System – Cost-Benefit Analysis
A2: Customer: Aerospace MRO Facility | Prepared by: Yadnesh Deshpande | Date: April 2026
A4: INVESTMENT
A5: EMMA System Purchase Price ($) | B5: 350000 | C5: ← Input (blue = editable)
A6: Installation & Setup ($) | B6: 12000 | C6: ← Input (blue = editable)
A7: Training ($) | B7: 8000 | C7: ← Input (blue = editable)
A8: Annual Maintenance ($) | B8: 18000 | C8: ← Input (blue = editable)
A9: Consumables per Year ($) | B9: 6500 | C9: ← Input (blue = editable)
A11: CURRENT STATE (Manual)
A12: Number of Manual Sanding Workers | B12: 6 | C12: ← Input (blue = editable)
A13: Average Worker Hourly Rate ($/hr) | B13: 28 | C13: ← Input (blue = editable)
A14: Hours Worked per Day | B14: 8 | C14: ← Input (blue = editable)
A15: Working Days per Year | B15: 250 | C15: ← Input (blue = editable)
A16: Rework Rate (% of jobs) | B16: 0.12 | C16: ← Input (blue = editable)
A17: Average Rework Cost per Job ($) | B17: 420 | C17: ← Input (blue = editable)
A18: Jobs per Year | B18: 800 | C18: ← Input (blue = editable)
A19: Worker Injury Rate (incidents/yr) | B19: 2 | C19: ← Input (blue = editable)
A20: Average Injury Cost ($) | B20: 15000 | C20: ← Input (blue = editable)
A21: EMMA PERFORMANCE
A22: EMMA Throughput vs Manual (%) | B22: 2.3 | C22: ← Input (blue = editable)
A23: EMMA Rework Rate (%) | B23: 0.02 | C23: ← Input (blue = editable)
A24: EMMA Operator Headcount (from 6 to) | B24: 1 | C24: ← Input (blue = editable)
A25: EMMA Uptime (%) | B25: 0.95 | C25: ← Input (blue = editable)

Sheet CBA Model
A1: EMMA™ Cost-Benefit Analysis – 5-Year Projection
A2: Item | B2: Year 1 | C2: Year 2 | D2: Year 3 | E2: Year 4 | F2: Year 5
A3: COSTS
A4: System Purchase | B4: =Assumptions!B5 | C4: - | D4: - | E4: - | F4: -
A5: Installation & Setup | B5: =Assumptions!B6 | C5: - | D5: - | E5: - | F5: -
A6: Training | B6: =Assumptions!B7 | C6: - | D6: - | E6: - | F6: -
A7: Annual Maintenance | B7: =Assumptions!B8 | C7: =Assumptions!B8 | D7: =Assumptions!B8 | E7: =Assumptions!B8 | F7: =Assumptions!B8
A8: Consumables | B8: =Assumptions!B9 | C8: =Assumptions!B9 | D8: =Assumptions!B9 | E8: =Assumptions!B9 | F8: =Assumptions!B9
A9: Total Annual Cost | B9: =SUM(B4:B8) | C9: =SUM(C4:C8) | D9: =SUM(D4:D8) | E9: =SUM(E4:E8) | F9: =SUM(F4:F8)
A10: SAVINGS
A11: Labor Savings | B11: =(Assumptions!B12-Assumptions!B23)*Assumptions!B13*Assumptions!B14*Assumptions!B15 | C11: =(Assumptions!B12-Assumptions!B23)*Assumptions!B13*Assumptions!B14*Assumptions!B15 | D11: =(Assumptions!B12-Assumptions!B23)*Assumptions!B13*Assumptions!B14*Assumptions!B15 | E11: =(Assumptions!B12-Assumptions!B23)*Assumptions!B13*Assumptions!B14*Assumptions!B15 | F11: =(Assumptions!B12-Assumptions!B23)*Assumptions!B13*Assumptions!B14*Assumptions!B15
A12: Rework Cost Reduction | B12: =(Assumptions!B16-Assumptions!B24)*Assumptions!B17*Assumptions!B18 | C12: =(Assumptions!B16-Assumptions!B24)*Assumptions!B17*Assumptions!B18 | D12: =(Assumptions!B16-Assumptions!B24)*Assumptions!B17*Assumptions!B18 | E12: =(Assumptions!B16-Assumptions!B24)*Assumptions!B17*Assumptions!B18 | F12: =(Assumptions!B16-Assumptions!B24)*Assumptions!B17*Assumptions!B18
A13: Injury Cost Avoided | B13: =Assumptions!B19*Assumptions!B20 | C13: =Assumptions!B19*Assumptions!B20 | D13: =Assumptions!B19*Assumptions!B20 | E13: =Assumptions!B19*Assumptions!B20 | F13: =Assumptions!B19*Assumptions!B20
A14: Total Annual Savings | B14: =SUM(B10:B12) | C14: =SUM(C10:C12) | D14: =SUM(D10:D12) | E14: =SUM(E10:E12) | F14: =SUM(F10:F12)
A15: NET BENEFIT
A16: Net Benefit (Savings–Cost) | B16: =B13-B9 | C16: =C13-C9 | D16: =D13-D9 | E16: =E13-E9 | F16: =F13-F9
A17: Cumulative Net Benefit | B17: =B15 | C17: =B15+C15 | D17: =B15+C15+D15 | E17: =B15+C15+D15+E15 | F17: =B15+C15+D15+E15+F15
A18: ROI (%) | B18: =B13/B9 | C18: =C13/C9 | D18: =D13/D9 | E18: =E13/E9 | F18: =F13/F9

Sheet Executive Summary
A1: EMMA™ Investment – Executive Summary
A3: Total 5-Year Investment | B3: ='CBA Model'!B9+'CBA Model'!C9+'CBA Model'!D9+'CBA Model'!E9+'CBA Model'!F9
A4: Total 5-Year Savings | B4: ='CBA Model'!B13+'CBA Model'!C13+'CBA Model'!D13+'CBA Model'!E13+'CBA Model'!F13
A5: 5-Year Net Benefit | B5: ='CBA Model'!F16
A6: Payback Period (approx yrs) | B6: =('CBA Model'!B9)/('CBA Model'!B13)
A7: 5-Year Average ROI | B7: =AVERAGE('CBA Model'!B17,'CBA Model'!C17,'CBA Model'!D17,'CBA Model'!E17,'CBA Model'!F17)
A8: Labor Headcount Reduction | B8: =Assumptions!B12-Assumptions!B23
